{"cameraMode":{"drawMode":0,"name":"Shaded","section":"Shading Mode"},"sceneLighting":true,"audioPlay":false,"sceneViewState":{"m_AlwaysRefresh":false,"showFog":true,"showSkybox":true,"showFlares":true,"showImageEffects":true,"showParticleSystems":true,"showVisualEffectGraphs":true,"m_FxEnabled":true},"in2DMode":false,"pivot":{"x":795.30224609375,"y":7.775452613830566,"z":77.73298645019531},"rotation":{"x":-0.03433004766702652,"y":-0.9554893970489502,"z":0.12336499989032746,"w":-0.26596710085868838},"size":28.733793258666993,"orthographic":false}